vmware_nsx_tempest_plugin/__init__.py
vmware_nsx_tempest_plugin/_i18n.py
vmware_nsx_tempest_plugin/config.py
vmware_nsx_tempest_plugin/plugin.py
vmware_nsx_tempest_plugin/common/__init__.py
vmware_nsx_tempest_plugin/common/constants.py
vmware_nsx_tempest_plugin/common/models.py
vmware_nsx_tempest_plugin/common/waiters.py
vmware_nsx_tempest_plugin/doc/README-AdminPolicy.rst
vmware_nsx_tempest_plugin/doc/README-LBaaS.rst
vmware_nsx_tempest_plugin/doc/admin-policy-AA.blueprint
vmware_nsx_tempest_plugin/doc/admin-policy-BB.blueprint
vmware_nsx_tempest_plugin/lib/__init__.py
vmware_nsx_tempest_plugin/lib/appliance_manager.py
vmware_nsx_tempest_plugin/lib/feature_manager.py
vmware_nsx_tempest_plugin/lib/traffic_manager.py
vmware_nsx_tempest_plugin/services/README.rst
vmware_nsx_tempest_plugin/services/__init__.py
vmware_nsx_tempest_plugin/services/base_l2gw.py
vmware_nsx_tempest_plugin/services/designate_base.py
vmware_nsx_tempest_plugin/services/fwaas_client.py
vmware_nsx_tempest_plugin/services/l2_gateway_client.py
vmware_nsx_tempest_plugin/services/l2_gateway_connection_client.py
vmware_nsx_tempest_plugin/services/load_balancer_v1_client.py
vmware_nsx_tempest_plugin/services/network_client_base.py
vmware_nsx_tempest_plugin/services/nsx_client.py
vmware_nsx_tempest_plugin/services/nsxv3_client.py
vmware_nsx_tempest_plugin/services/nsxv_client.py
vmware_nsx_tempest_plugin/services/openstack_network_clients.py
vmware_nsx_tempest_plugin/services/tags_client.py
vmware_nsx_tempest_plugin/services/utils.py
vmware_nsx_tempest_plugin/services/lbaas/__init__.py
vmware_nsx_tempest_plugin/services/lbaas/health_monitors_client.py
vmware_nsx_tempest_plugin/services/lbaas/l7policies_client.py
vmware_nsx_tempest_plugin/services/lbaas/l7rules_client.py
vmware_nsx_tempest_plugin/services/lbaas/listeners_client.py
vmware_nsx_tempest_plugin/services/lbaas/load_balancers_client.py
vmware_nsx_tempest_plugin/services/lbaas/members_client.py
vmware_nsx_tempest_plugin-1.0.0.dist-info/METADATA
vmware_nsx_tempest_plugin-1.0.0.dist-info/RECORD
vmware_nsx_tempest_plugin-1.0.0.dist-info/WHEEL
vmware_nsx_tempest_plugin-1.0.0.dist-info/entry_points.txt
vmware_nsx_tempest_plugin-1.0.0.dist-info/pbr.json
vmware_nsx_tempest_plugin-1.0.0.dist-info/top_level.txt
